pywe_exception/__init__.py
pywe_exception/exception.py
pywe_exception-1.0.2.dist-info/DESCRIPTION.rst
pywe_exception-1.0.2.dist-info/METADATA
pywe_exception-1.0.2.dist-info/RECORD
pywe_exception-1.0.2.dist-info/WHEEL
pywe_exception-1.0.2.dist-info/metadata.json
pywe_exception-1.0.2.dist-info/top_level.txt
